mqtt_text2speech/client.py
mqtt_text2speech/config.py
mqtt_text2speech-0.1.1.dist-info/METADATA
mqtt_text2speech-0.1.1.dist-info/WHEEL
mqtt_text2speech-0.1.1.dist-info/RECORD
