Metadata-Version: 2.1
Name: mqtt_text2speech
Version: 0.1.1
Summary: A simple MQTT audio client for synthesizing text messages published to an MQTT broker
Author: SimonThimm
Author-email: 2023463@stud.hs-mannheim.de
Requires-Python: >=3.10.12,<4.0.0
Classifier: Programming Language :: Python :: 3
Classifier: Programming Language :: Python :: 3.11
Classifier: Programming Language :: Python :: 3.12
Requires-Dist: paho-mqtt (>=2.1.0,<3.0.0)
Requires-Dist: python-dotenv (>=1.0.1,<2.0.0)
Requires-Dist: pyttsx3 (>=2.90,<3.0)
